Metadata-Version: 2.1
Name: sb3tools
Version: 0.0.2
Summary: Some tools about Scratch3.x
Author: Maswdle
Author-email: wondr009@163.com
License: UNKNOWN
Platform: UNKNOWN
